common/__init__.py
common/admin.py
common/apps.py
common/auth.py
common/commands.py
common/excel.py
common/fields.py
common/forms.py
common/logger.py
common/middleware.py
common/models.py
common/operations.py
common/router.py
common/runtests.py
common/settings.py
common/tasks.py
common/urls.py
common/utils.py
common/views.py
common/websocket.py
common/api/__init__.py
common/api/api_views.py
common/api/base.py
common/api/config.py
common/api/fields.py
common/api/input_serializers.py
common/api/pagination.py
common/api/permissions.py
common/api/renderers.py
common/api/serializers.py
common/api/urls.py
common/api/utils.py
common/api/viewsets.py
common/locale/en/LC_MESSAGES/django.po
common/locale/fr/LC_MESSAGES/django.po
common/management/__init__.py
common/management/commands/__init__.py
common/management/commands/abort_sql.py
common/management/commands/clear.py
common/management/commands/run_websocket.py
common/migrations/0001_initial_squashed_0015_auto_20231201.py
common/migrations/__init__.py
common/templates/common/cache.html
common/templates/common/delete_selected.html
common/templates/common/scripts.js
common/templatetags/__init__.py
common/templatetags/tools.py
common/tests/__init__.py
common/tests/test_api.py
common/tests/test_utils.py
common/tests/urls.py
common_framework-2025.9.9.dist-info/METADATA
common_framework-2025.9.9.dist-info/WHEEL
common_framework-2025.9.9.dist-info/licenses/LICENSE.txt
common_framework-2025.9.9.dist-info/RECORD
